voidbots/__init__.py
voidbots/main.py
voidbots-0.0.2.dist-info/METADATA
voidbots-0.0.2.dist-info/WHEEL
voidbots-0.0.2.dist-info/top_level.txt
voidbots-0.0.2.dist-info/RECORD
